Metadata-Version: 2.1
Name: clean-sqlalchemy
Version: 2.1.0b1.dev0
Summary: Database Abstraction Library
Author-email: Joey Elsisi <joeyelsisi@gmail.com>
License: MIT
Project-URL: Homepage, https://www.sqlalchemy.org
Project-URL: Documentation, https://docs.sqlalchemy.org
Project-URL: Changelog, https://docs.sqlalchemy.org/latest/changelog/index.html
Project-URL: Source Code, https://github.com/sqlalchemy/sqlalchemy
Project-URL: Issue Tracker, https://github.com/sqlalchemy/sqlalchemy/issues
Project-URL: Discussions, https://github.com/sqlalchemy/sqlalchemy/discussions
Classifier: Development Status :: 5 - Production/Stable
Classifier: Intended Audience :: Developers
Classifier: License :: OSI Approved :: MIT License
Classifier: Operating System :: OS Independent
Classifier: Programming Language :: Python
Classifier: Programming Language :: Python :: 3
Classifier: Programming Language :: Python :: 3.9
Classifier: Programming Language :: Python :: 3.10
Classifier: Programming Language :: Python :: 3.11
Classifier: Programming Language :: Python :: 3.12
Classifier: Programming Language :: Python :: 3.13
Classifier: Programming Language :: Python :: Implementation :: CPython
Classifier: Programming Language :: Python :: Implementation :: PyPy
Classifier: Topic :: Database :: Front-Ends
Requires-Python: >=3.9
License-File: LICENSE
Requires-Dist: typing-extensions >=4.6.0
Provides-Extra: aiomysql
Requires-Dist: greenlet !=0.4.17 ; extra == 'aiomysql'
Requires-Dist: aiomysql ; extra == 'aiomysql'
Provides-Extra: aioodbc
Requires-Dist: greenlet !=0.4.17 ; extra == 'aioodbc'
Requires-Dist: aioodbc ; extra == 'aioodbc'
Provides-Extra: aiosqlite
Requires-Dist: greenlet !=0.4.17 ; extra == 'aiosqlite'
Requires-Dist: aiosqlite ; extra == 'aiosqlite'
Provides-Extra: asyncio
Requires-Dist: greenlet !=0.4.17 ; extra == 'asyncio'
Provides-Extra: asyncmy
Requires-Dist: greenlet !=0.4.17 ; extra == 'asyncmy'
Requires-Dist: asyncmy !=0.2.4,!=0.2.6,>=0.2.3 ; extra == 'asyncmy'
Provides-Extra: mariadb-connector
Requires-Dist: mariadb !=1.1.10,!=1.1.2,!=1.1.5,>=1.0.1 ; extra == 'mariadb-connector'
Provides-Extra: mariadb_connector
Requires-Dist: sqlalchemy[mariadb-connector] ; extra == 'mariadb_connector'
Provides-Extra: mssql
Requires-Dist: pyodbc ; extra == 'mssql'
Provides-Extra: mssql-pymssql
Requires-Dist: pymssql ; extra == 'mssql-pymssql'
Provides-Extra: mssql-pyodbc
Requires-Dist: pyodbc ; extra == 'mssql-pyodbc'
Provides-Extra: mssql_pymssql
Requires-Dist: sqlalchemy[mssql-pymssql] ; extra == 'mssql_pymssql'
Provides-Extra: mssql_pyodbc
Requires-Dist: sqlalchemy[mssql-pyodbc] ; extra == 'mssql_pyodbc'
Provides-Extra: mypy
Requires-Dist: mypy >=1.7 ; extra == 'mypy'
Requires-Dist: types-greenlet >=2 ; extra == 'mypy'
Provides-Extra: mysql
Requires-Dist: mysqlclient >=1.4.0 ; extra == 'mysql'
Provides-Extra: mysql-connector
Requires-Dist: mysql-connector-python ; extra == 'mysql-connector'
Provides-Extra: mysql_connector
Requires-Dist: sqlalchemy[mysql-connector] ; extra == 'mysql_connector'
Provides-Extra: oracle
Requires-Dist: cx-oracle >=8 ; extra == 'oracle'
Provides-Extra: oracle-oracledb
Requires-Dist: oracledb >=1.0.1 ; extra == 'oracle-oracledb'
Provides-Extra: oracle_oracledb
Requires-Dist: sqlalchemy[oracle-oracledb] ; extra == 'oracle_oracledb'
Provides-Extra: postgresql
Requires-Dist: psycopg2 >=2.7 ; extra == 'postgresql'
Provides-Extra: postgresql-asyncpg
Requires-Dist: greenlet !=0.4.17 ; extra == 'postgresql-asyncpg'
Requires-Dist: asyncpg ; extra == 'postgresql-asyncpg'
Provides-Extra: postgresql-pg8000
Requires-Dist: pg8000 >=1.29.3 ; extra == 'postgresql-pg8000'
Provides-Extra: postgresql-psycopg
Requires-Dist: psycopg !=3.1.15,>=3.0.7 ; extra == 'postgresql-psycopg'
Provides-Extra: postgresql-psycopg2binary
Requires-Dist: psycopg2-binary ; extra == 'postgresql-psycopg2binary'
Provides-Extra: postgresql-psycopg2cffi
Requires-Dist: psycopg2cffi ; extra == 'postgresql-psycopg2cffi'
Provides-Extra: postgresql-psycopgbinary
Requires-Dist: psycopg[binary] !=3.1.15,>=3.0.7 ; extra == 'postgresql-psycopgbinary'
Provides-Extra: postgresql_asyncpg
Requires-Dist: sqlalchemy[postgresql-asyncpg] ; extra == 'postgresql_asyncpg'
Provides-Extra: postgresql_pg8000
Requires-Dist: sqlalchemy[postgresql-pg8000] ; extra == 'postgresql_pg8000'
Provides-Extra: postgresql_psycopg
Requires-Dist: sqlalchemy[postgresql-psycopg] ; extra == 'postgresql_psycopg'
Provides-Extra: postgresql_psycopg2binary
Requires-Dist: sqlalchemy[postgresql-psycopg2binary] ; extra == 'postgresql_psycopg2binary'
Provides-Extra: postgresql_psycopg2cffi
Requires-Dist: sqlalchemy[postgresql-psycopg2cffi] ; extra == 'postgresql_psycopg2cffi'
Provides-Extra: postgresql_psycopgbinary
Requires-Dist: sqlalchemy[postgresql-psycopgbinary] ; extra == 'postgresql_psycopgbinary'
Provides-Extra: pymysql
Requires-Dist: pymysql ; extra == 'pymysql'
Provides-Extra: sqlcipher
Requires-Dist: sqlcipher3-binary ; extra == 'sqlcipher'
